<?xml version="1.0"?>
<dolfin xmlns:dolfin="http://fenicsproject.org">
  <function_data size="289">
    <dof index="0" value="136.64817419621122" cell_index="113" cell_dof_index="1" />
    <dof index="1" value="40.471685182169566" cell_index="97" cell_dof_index="1" />
    <dof index="2" value="44.946778654284387" cell_index="112" cell_dof_index="2" />
    <dof index="3" value="-16.412740052874245" cell_index="112" cell_dof_index="4" />
    <dof index="4" value="54.32822536671879" cell_index="113" cell_dof_index="3" />
    <dof index="5" value="55.446998734746629" cell_index="113" cell_dof_index="5" />
    <dof index="6" value="13.579655157139564" cell_index="81" cell_dof_index="1" />
    <dof index="7" value="9.2449658721705266" cell_index="96" cell_dof_index="2" />
    <dof index="8" value="-9.6663002319297888" cell_index="96" cell_dof_index="4" />
    <dof index="9" value="-1.5576015514873118" cell_index="97" cell_dof_index="3" />
    <dof index="10" value="24.476297172171314" cell_index="97" cell_dof_index="5" />
    <dof index="11" value="-0.56515813948808047" cell_index="112" cell_dof_index="3" />
    <dof index="12" value="19.126424558411681" cell_index="114" cell_dof_index="2" />
    <dof index="13" value="-8.3722090475066455" cell_index="114" cell_dof_index="4" />
    <dof index="14" value="26.193265013881582" cell_index="115" cell_dof_index="3" />
    <dof index="15" value="-3.2893749734673823" cell_index="65" cell_dof_index="1" />
    <dof index="16" value="1.116409933210778" cell_index="80" cell_dof_index="2" />
    <dof index="17" value="-10.470429950006469" cell_index="80" cell_dof_index="4" />
    <dof index="18" value="-6.1499291216602003" cell_index="81" cell_dof_index="3" />
    <dof index="19" value="11.92795185118872" cell_index="81" cell_dof_index="5" />
    <dof index="20" value="2.0856132795317559" cell_index="96" cell_dof_index="3" />
    <dof index="21" value="-14.126633475303603" cell_index="98" cell_dof_index="2" />
    <dof index="22" value="-17.240909624820553" cell_index="98" cell_dof_index="4" />
    <dof index="23" value="0.50366843650832127" cell_index="99" cell_dof_index="3" />
    <dof index="24" value="-1.3188942322555075" cell_index="114" cell_dof_index="3" />
    <dof index="25" value="28.529244701099095" cell_index="116" cell_dof_index="2" />
    <dof index="26" value="-14.246956347082287" cell_index="116" cell_dof_index="4" />
    <dof index="27" value="18.185948747721849" cell_index="117" cell_dof_index="3" />
    <dof index="28" value="1.9575869630576963" cell_index="49" cell_dof_index="1" />
    <dof index="29" value="11.024135112333513" cell_index="64" cell_dof_index="2" />
    <dof index="30" value="-5.1128822179220048" cell_index="64" cell_dof_index="4" />
    <dof index="31" value="-5.8643847123218054" cell_index="65" cell_dof_index="3" />
    <dof index="32" value="-14.581991418092338" cell_index="65" cell_dof_index="5" />
    <dof index="33" value="-4.8127613075311722" cell_index="80" cell_dof_index="3" />
    <dof index="34" value="62.762055556416904" cell_index="82" cell_dof_index="2" />
    <dof index="35" value="41.65223169694891" cell_index="82" cell_dof_index="4" />
    <dof index="36" value="-8.54060427558586" cell_index="83" cell_dof_index="3" />
    <dof index="37" value="-1.7002839186299803" cell_index="98" cell_dof_index="3" />
    <dof index="38" value="36.449124235669856" cell_index="100" cell_dof_index="2" />
    <dof index="39" value="30.429111240080704" cell_index="100" cell_dof_index="4" />
    <dof index="40" value="-3.9047138928635068" cell_index="101" cell_dof_index="3" />
    <dof index="41" value="-27.187219139972214" cell_index="116" cell_dof_index="3" />
    <dof index="42" value="-6.6557074594188936" cell_index="118" cell_dof_index="2" />
    <dof index="43" value="38.894667182426623" cell_index="118" cell_dof_index="4" />
    <dof index="44" value="-35.255135864558703" cell_index="119" cell_dof_index="3" />
    <dof index="45" value="6.2093399814835921" cell_index="33" cell_dof_index="1" />
    <dof index="46" value="-13.683948517254347" cell_index="48" cell_dof_index="2" />
    <dof index="47" value="-6.5966877455981576" cell_index="48" cell_dof_index="4" />
    <dof index="48" value="-1.625952270158501" cell_index="49" cell_dof_index="3" />
    <dof index="49" value="-1.4195526628642918" cell_index="49" cell_dof_index="5" />
    <dof index="50" value="1.3241201360336383" cell_index="64" cell_dof_index="3" />
    <dof index="51" value="17.654309646724084" cell_index="66" cell_dof_index="2" />
    <dof index="52" value="-0.30893114140775302" cell_index="66" cell_dof_index="4" />
    <dof index="53" value="-17.453719864085208" cell_index="67" cell_dof_index="3" />
    <dof index="54" value="-36.604482496050267" cell_index="82" cell_dof_index="3" />
    <dof index="55" value="26.715677677635188" cell_index="84" cell_dof_index="2" />
    <dof index="56" value="44.928659850669419" cell_index="84" cell_dof_index="4" />
    <dof index="57" value="-14.25652782937461" cell_index="85" cell_dof_index="3" />
    <dof index="58" value="-7.1054786666010621" cell_index="100" cell_dof_index="3" />
    <dof index="59" value="27.102133668070195" cell_index="102" cell_dof_index="2" />
    <dof index="60" value="21.078024444617867" cell_index="102" cell_dof_index="4" />
    <dof index="61" value="-19.734279759973415" cell_index="103" cell_dof_index="3" />
    <dof index="62" value="-11.725465383832917" cell_index="118" cell_dof_index="3" />
    <dof index="63" value="12.813919017643498" cell_index="120" cell_dof_index="2" />
    <dof index="64" value="18.075630801199583" cell_index="120" cell_dof_index="4" />
    <dof index="65" value="-7.3056744012463302" cell_index="121" cell_dof_index="3" />
    <dof index="66" value="17.480186790543232" cell_index="17" cell_dof_index="1" />
    <dof index="67" value="53.347379184195347" cell_index="32" cell_dof_index="2" />
    <dof index="68" value="59.791438473789349" cell_index="32" cell_dof_index="4" />
    <dof index="69" value="-4.7156793194642903" cell_index="33" cell_dof_index="3" />
    <dof index="70" value="-35.777142527079427" cell_index="33" cell_dof_index="5" />
    <dof index="71" value="-0.26239370317323862" cell_index="48" cell_dof_index="3" />
    <dof index="72" value="-9.783574813023229" cell_index="50" cell_dof_index="2" />
    <dof index="73" value="23.326324861029768" cell_index="50" cell_dof_index="4" />
    <dof index="74" value="22.334148944953085" cell_index="51" cell_dof_index="3" />
    <dof index="75" value="19.132666956776557" cell_index="66" cell_dof_index="3" />
    <dof index="76" value="78.516198895594243" cell_index="68" cell_dof_index="2" />
    <dof index="77" value="20.937765799711194" cell_index="68" cell_dof_index="4" />
    <dof index="78" value="-6.1225653584724622" cell_index="69" cell_dof_index="3" />
    <dof index="79" value="-21.704893654160948" cell_index="84" cell_dof_index="3" />
    <dof index="80" value="2.4653408653076796" cell_index="86" cell_dof_index="2" />
    <dof index="81" value="52.168666912199441" cell_index="86" cell_dof_index="4" />
    <dof index="82" value="-2.2630358283024492" cell_index="87" cell_dof_index="3" />
    <dof index="83" value="15.881800470766301" cell_index="102" cell_dof_index="3" />
    <dof index="84" value="52.852748224085857" cell_index="104" cell_dof_index="2" />
    <dof index="85" value="25.358626254837418" cell_index="104" cell_dof_index="4" />
    <dof index="86" value="-1.3108157354673491" cell_index="105" cell_dof_index="3" />
    <dof index="87" value="-2.6821066593911498" cell_index="120" cell_dof_index="3" />
    <dof index="88" value="27.06004455108949" cell_index="122" cell_dof_index="2" />
    <dof index="89" value="57.510950924251333" cell_index="122" cell_dof_index="4" />
    <dof index="90" value="-31.634920793036009" cell_index="123" cell_dof_index="3" />
    <dof index="91" value="-40.196537317877215" cell_index="1" cell_dof_index="1" />
    <dof index="92" value="29.462085299016469" cell_index="16" cell_dof_index="2" />
    <dof index="93" value="26.304579961513628" cell_index="16" cell_dof_index="4" />
    <dof index="94" value="1.2326443287455646" cell_index="17" cell_dof_index="3" />
    <dof index="95" value="-3.4132346673628291" cell_index="17" cell_dof_index="5" />
    <dof index="96" value="-28.067014656427386" cell_index="32" cell_dof_index="3" />
    <dof index="97" value="15.272860070285024" cell_index="34" cell_dof_index="2" />
    <dof index="98" value="46.943808493205765" cell_index="34" cell_dof_index="4" />
    <dof index="99" value="-19.040589227358513" cell_index="35" cell_dof_index="3" />
    <dof index="100" value="6.2566465270131193" cell_index="50" cell_dof_index="3" />
    <dof index="101" value="16.072518608192219" cell_index="52" cell_dof_index="2" />
    <dof index="102" value="-6.559975640674347" cell_index="52" cell_dof_index="4" />
    <dof index="103" value="3.5753851534731265" cell_index="53" cell_dof_index="3" />
    <dof index="104" value="-28.976148186529063" cell_index="68" cell_dof_index="3" />
    <dof index="105" value="25.412383538481077" cell_index="70" cell_dof_index="2" />
    <dof index="106" value="33.310624912865755" cell_index="70" cell_dof_index="4" />
    <dof index="107" value="-32.628664092066238" cell_index="71" cell_dof_index="3" />
    <dof index="108" value="-20.307743634916601" cell_index="86" cell_dof_index="3" />
    <dof index="109" value="89.414950421059629" cell_index="88" cell_dof_index="2" />
    <dof index="110" value="51.532633594006803" cell_index="88" cell_dof_index="4" />
    <dof index="111" value="-23.342620128037073" cell_index="89" cell_dof_index="3" />
    <dof index="112" value="-33.138954274398486" cell_index="104" cell_dof_index="3" />
    <dof index="113" value="30.59346534278929" cell_index="106" cell_dof_index="2" />
    <dof index="114" value="79.546263809854651" cell_index="106" cell_dof_index="4" />
    <dof index="115" value="-30.301873984145274" cell_index="107" cell_dof_index="3" />
    <dof index="116" value="0.99690216262278497" cell_index="122" cell_dof_index="3" />
    <dof index="117" value="-42.311680098155975" cell_index="124" cell_dof_index="2" />
    <dof index="118" value="16.416469892365203" cell_index="124" cell_dof_index="4" />
    <dof index="119" value="-5.950672758645573" cell_index="125" cell_dof_index="3" />
    <dof index="120" value="-165.0686127041775" cell_index="0" cell_dof_index="0" />
    <dof index="121" value="-5.222768469793718" cell_index="0" cell_dof_index="2" />
    <dof index="122" value="-14.352119571088842" cell_index="0" cell_dof_index="4" />
    <dof index="123" value="7.6740951004702538" cell_index="1" cell_dof_index="3" />
    <dof index="124" value="-21.175361392529339" cell_index="1" cell_dof_index="5" />
    <dof index="125" value="-28.419272701268728" cell_index="16" cell_dof_index="3" />
    <dof index="126" value="-1.2505918715332589" cell_index="18" cell_dof_index="2" />
    <dof index="127" value="19.838341565204885" cell_index="18" cell_dof_index="4" />
    <dof index="128" value="-50.40600366393128" cell_index="19" cell_dof_index="3" />
    <dof index="129" value="-21.193337948763912" cell_index="34" cell_dof_index="3" />
    <dof index="130" value="-12.537463569451926" cell_index="36" cell_dof_index="2" />
    <dof index="131" value="-5.0798683552978154" cell_index="36" cell_dof_index="4" />
    <dof index="132" value="4.3204282655610342" cell_index="37" cell_dof_index="3" />
    <dof index="133" value="18.385533257567044" cell_index="52" cell_dof_index="3" />
    <dof index="134" value="35.39296204895254" cell_index="54" cell_dof_index="2" />
    <dof index="135" value="-6.9720984426357706" cell_index="54" cell_dof_index="4" />
    <dof index="136" value="12.122856638088635" cell_index="55" cell_dof_index="3" />
    <dof index="137" value="0.84394595844911358" cell_index="70" cell_dof_index="3" />
    <dof index="138" value="-6.3464177927450933" cell_index="72" cell_dof_index="2" />
    <dof index="139" value="5.2533170564819667" cell_index="72" cell_dof_index="4" />
    <dof index="140" value="4.4578967830827381" cell_index="73" cell_dof_index="3" />
    <dof index="141" value="-17.864348248041132" cell_index="88" cell_dof_index="3" />
    <dof index="142" value="-11.233675113433897" cell_index="90" cell_dof_index="2" />
    <dof index="143" value="6.6554804681007358" cell_index="90" cell_dof_index="4" />
    <dof index="144" value="-45.489890868437598" cell_index="91" cell_dof_index="3" />
    <dof index="145" value="-34.074817167874635" cell_index="106" cell_dof_index="3" />
    <dof index="146" value="-11.903205055729309" cell_index="108" cell_dof_index="2" />
    <dof index="147" value="23.218154480400415" cell_index="108" cell_dof_index="4" />
    <dof index="148" value="-15.51274086507194" cell_index="109" cell_dof_index="3" />
    <dof index="149" value="-4.6205181571086449" cell_index="124" cell_dof_index="3" />
    <dof index="150" value="-144.47535537566574" cell_index="126" cell_dof_index="2" />
    <dof index="151" value="-10.845822204030538" cell_index="126" cell_dof_index="4" />
    <dof index="152" value="-35.071374213330913" cell_index="127" cell_dof_index="3" />
    <dof index="153" value="-50.587240948841171" cell_index="0" cell_dof_index="1" />
    <dof index="154" value="8.1425479794686577" cell_index="0" cell_dof_index="3" />
    <dof index="155" value="-38.479033292345328" cell_index="0" cell_dof_index="5" />
    <dof index="156" value="12.155000122221368" cell_index="2" cell_dof_index="2" />
    <dof index="157" value="11.832473390595233" cell_index="2" cell_dof_index="4" />
    <dof index="158" value="0.1301169452530635" cell_index="3" cell_dof_index="3" />
    <dof index="159" value="2.6167297270031775" cell_index="18" cell_dof_index="3" />
    <dof index="160" value="25.386725740887588" cell_index="20" cell_dof_index="2" />
    <dof index="161" value="34.609777447755924" cell_index="20" cell_dof_index="4" />
    <dof index="162" value="5.7655102716744739" cell_index="21" cell_dof_index="3" />
    <dof index="163" value="-8.2246312242113611" cell_index="36" cell_dof_index="3" />
    <dof index="164" value="4.558190366129935" cell_index="38" cell_dof_index="2" />
    <dof index="165" value="19.212420998825362" cell_index="38" cell_dof_index="4" />
    <dof index="166" value="-11.895914012756418" cell_index="39" cell_dof_index="3" />
    <dof index="167" value="-9.8763260254247953" cell_index="54" cell_dof_index="3" />
    <dof index="168" value="-13.6117095841748" cell_index="56" cell_dof_index="2" />
    <dof index="169" value="22.501519058168434" cell_index="56" cell_dof_index="4" />
    <dof index="170" value="-5.8042172190268708" cell_index="57" cell_dof_index="3" />
    <dof index="171" value="-4.6801860910772373" cell_index="72" cell_dof_index="3" />
    <dof index="172" value="16.057886303784848" cell_index="74" cell_dof_index="2" />
    <dof index="173" value="24.881997200118409" cell_index="74" cell_dof_index="4" />
    <dof index="174" value="3.3449647684068866" cell_index="75" cell_dof_index="3" />
    <dof index="175" value="26.49720719378341" cell_index="90" cell_dof_index="3" />
    <dof index="176" value="-35.114805279941294" cell_index="92" cell_dof_index="2" />
    <dof index="177" value="-44.81529462436847" cell_index="92" cell_dof_index="4" />
    <dof index="178" value="25.626191803808133" cell_index="93" cell_dof_index="3" />
    <dof index="179" value="-14.582222073420114" cell_index="108" cell_dof_index="3" />
    <dof index="180" value="-25.461429984694281" cell_index="110" cell_dof_index="2" />
    <dof index="181" value="1.5824888276617806" cell_index="110" cell_dof_index="4" />
    <dof index="182" value="-9.5169658993085235" cell_index="111" cell_dof_index="3" />
    <dof index="183" value="-21.83276053958318" cell_index="126" cell_dof_index="3" />
    <dof index="184" value="5.3622406681030563" cell_index="2" cell_dof_index="1" />
    <dof index="185" value="-13.842314884968138" cell_index="2" cell_dof_index="3" />
    <dof index="186" value="-22.205202884141144" cell_index="2" cell_dof_index="5" />
    <dof index="187" value="17.067597046365783" cell_index="4" cell_dof_index="2" />
    <dof index="188" value="18.033197576075843" cell_index="4" cell_dof_index="4" />
    <dof index="189" value="-37.37172137070678" cell_index="5" cell_dof_index="3" />
    <dof index="190" value="-44.406272817348039" cell_index="20" cell_dof_index="3" />
    <dof index="191" value="-17.730035315943542" cell_index="22" cell_dof_index="2" />
    <dof index="192" value="-10.800308541511992" cell_index="22" cell_dof_index="4" />
    <dof index="193" value="-15.196022421847916" cell_index="23" cell_dof_index="3" />
    <dof index="194" value="-8.9409793636053259" cell_index="38" cell_dof_index="3" />
    <dof index="195" value="17.269664159358257" cell_index="40" cell_dof_index="2" />
    <dof index="196" value="1.6823196458376621" cell_index="40" cell_dof_index="4" />
    <dof index="197" value="-30.88152821951558" cell_index="41" cell_dof_index="3" />
    <dof index="198" value="-7.9418500608935556" cell_index="56" cell_dof_index="3" />
    <dof index="199" value="-92.501958332865513" cell_index="58" cell_dof_index="2" />
    <dof index="200" value="-82.367168594059009" cell_index="58" cell_dof_index="4" />
    <dof index="201" value="1.8059180672584656" cell_index="59" cell_dof_index="3" />
    <dof index="202" value="-6.2805669428459918" cell_index="74" cell_dof_index="3" />
    <dof index="203" value="29.050100024031703" cell_index="76" cell_dof_index="2" />
    <dof index="204" value="4.1868717099387336" cell_index="76" cell_dof_index="4" />
    <dof index="205" value="-7.5008799478141803" cell_index="77" cell_dof_index="3" />
    <dof index="206" value="7.4614467504672808" cell_index="92" cell_dof_index="3" />
    <dof index="207" value="-37.283375406643685" cell_index="94" cell_dof_index="2" />
    <dof index="208" value="16.192760633588268" cell_index="94" cell_dof_index="4" />
    <dof index="209" value="10.956269365872981" cell_index="95" cell_dof_index="3" />
    <dof index="210" value="-47.622914058983682" cell_index="110" cell_dof_index="3" />
    <dof index="211" value="12.493648223171045" cell_index="4" cell_dof_index="1" />
    <dof index="212" value="9.7964811246655845" cell_index="4" cell_dof_index="3" />
    <dof index="213" value="-13.732098826799918" cell_index="4" cell_dof_index="5" />
    <dof index="214" value="3.253752433114192" cell_index="6" cell_dof_index="2" />
    <dof index="215" value="3.4948819054385303" cell_index="6" cell_dof_index="4" />
    <dof index="216" value="4.617449952740933" cell_index="7" cell_dof_index="3" />
    <dof index="217" value="-9.8129745827659427" cell_index="22" cell_dof_index="3" />
    <dof index="218" value="-13.165178497178129" cell_index="24" cell_dof_index="2" />
    <dof index="219" value="13.967971107031643" cell_index="24" cell_dof_index="4" />
    <dof index="220" value="-21.523847352569195" cell_index="25" cell_dof_index="3" />
    <dof index="221" value="-32.180326038492709" cell_index="40" cell_dof_index="3" />
    <dof index="222" value="34.53576468075299" cell_index="42" cell_dof_index="2" />
    <dof index="223" value="22.083238804430152" cell_index="42" cell_dof_index="4" />
    <dof index="224" value="1.4738884245681447" cell_index="43" cell_dof_index="3" />
    <dof index="225" value="6.6255559173089864" cell_index="58" cell_dof_index="3" />
    <dof index="226" value="8.2799096204837994" cell_index="60" cell_dof_index="2" />
    <dof index="227" value="25.786744765005317" cell_index="60" cell_dof_index="4" />
    <dof index="228" value="-10.20887991222382" cell_index="61" cell_dof_index="3" />
    <dof index="229" value="-22.157837195872439" cell_index="76" cell_dof_index="3" />
    <dof index="230" value="28.472610913872998" cell_index="78" cell_dof_index="2" />
    <dof index="231" value="-17.05658710465724" cell_index="78" cell_dof_index="4" />
    <dof index="232" value="-38.695613894324083" cell_index="79" cell_dof_index="3" />
    <dof index="233" value="-32.291758148726942" cell_index="94" cell_dof_index="3" />
    <dof index="234" value="-10.022493587174077" cell_index="6" cell_dof_index="1" />
    <dof index="235" value="13.433449066230562" cell_index="6" cell_dof_index="3" />
    <dof index="236" value="4.4374533990805478" cell_index="6" cell_dof_index="5" />
    <dof index="237" value="-3.5913380378405142" cell_index="8" cell_dof_index="2" />
    <dof index="238" value="-10.134318315384633" cell_index="8" cell_dof_index="4" />
    <dof index="239" value="1.9706502972576605" cell_index="9" cell_dof_index="3" />
    <dof index="240" value="27.459386297503507" cell_index="24" cell_dof_index="3" />
    <dof index="241" value="4.0936533889363318" cell_index="26" cell_dof_index="2" />
    <dof index="242" value="-33.129090050536135" cell_index="26" cell_dof_index="4" />
    <dof index="243" value="42.42728797788498" cell_index="27" cell_dof_index="3" />
    <dof index="244" value="12.172925533367676" cell_index="42" cell_dof_index="3" />
    <dof index="245" value="17.240300633235599" cell_index="44" cell_dof_index="2" />
    <dof index="246" value="12.786970693740408" cell_index="44" cell_dof_index="4" />
    <dof index="247" value="-22.392346199559896" cell_index="45" cell_dof_index="3" />
    <dof index="248" value="13.778229038403683" cell_index="60" cell_dof_index="3" />
    <dof index="249" value="-40.51711421265621" cell_index="62" cell_dof_index="2" />
    <dof index="250" value="1.9901990895968158" cell_index="62" cell_dof_index="4" />
    <dof index="251" value="48.309987748196804" cell_index="63" cell_dof_index="3" />
    <dof index="252" value="-0.23776265339217728" cell_index="78" cell_dof_index="3" />
    <dof index="253" value="-4.6706012943809183" cell_index="8" cell_dof_index="1" />
    <dof index="254" value="1.1010359501747125" cell_index="8" cell_dof_index="3" />
    <dof index="255" value="3.8220016977250504" cell_index="8" cell_dof_index="5" />
    <dof index="256" value="-23.272460457292166" cell_index="10" cell_dof_index="2" />
    <dof index="257" value="-1.6719972681737152" cell_index="10" cell_dof_index="4" />
    <dof index="258" value="-5.7620485556891321" cell_index="11" cell_dof_index="3" />
    <dof index="259" value="14.646562872918118" cell_index="26" cell_dof_index="3" />
    <dof index="260" value="10.470887515125613" cell_index="28" cell_dof_index="2" />
    <dof index="261" value="-16.083919103639587" cell_index="28" cell_dof_index="4" />
    <dof index="262" value="7.3331044002115142" cell_index="29" cell_dof_index="3" />
    <dof index="263" value="-21.645328480803109" cell_index="44" cell_dof_index="3" />
    <dof index="264" value="23.740748750848546" cell_index="46" cell_dof_index="2" />
    <dof index="265" value="20.145802714507397" cell_index="46" cell_dof_index="4" />
    <dof index="266" value="-3.9533722508520341" cell_index="47" cell_dof_index="3" />
    <dof index="267" value="25.579320868163663" cell_index="62" cell_dof_index="3" />
    <dof index="268" value="21.834149362993735" cell_index="10" cell_dof_index="1" />
    <dof index="269" value="-9.8325125611757667" cell_index="10" cell_dof_index="3" />
    <dof index="270" value="7.3388317103436886" cell_index="10" cell_dof_index="5" />
    <dof index="271" value="12.776686578381607" cell_index="12" cell_dof_index="2" />
    <dof index="272" value="-20.098461812381942" cell_index="12" cell_dof_index="4" />
    <dof index="273" value="15.501990887669459" cell_index="13" cell_dof_index="3" />
    <dof index="274" value="14.948693942091799" cell_index="28" cell_dof_index="3" />
    <dof index="275" value="21.832809453301188" cell_index="30" cell_dof_index="2" />
    <dof index="276" value="1.2392706164666079" cell_index="30" cell_dof_index="4" />
    <dof index="277" value="-4.6146590913036025" cell_index="31" cell_dof_index="3" />
    <dof index="278" value="11.777960052514532" cell_index="46" cell_dof_index="3" />
    <dof index="279" value="39.579192862244248" cell_index="12" cell_dof_index="1" />
    <dof index="280" value="2.3188769299850507" cell_index="12" cell_dof_index="3" />
    <dof index="281" value="28.653222445797422" cell_index="12" cell_dof_index="5" />
    <dof index="282" value="45.915705105717741" cell_index="14" cell_dof_index="2" />
    <dof index="283" value="-16.936319912648468" cell_index="14" cell_dof_index="4" />
    <dof index="284" value="-1.4398739974220751" cell_index="15" cell_dof_index="3" />
    <dof index="285" value="22.720183629275592" cell_index="30" cell_dof_index="3" />
    <dof index="286" value="136.31185997827976" cell_index="14" cell_dof_index="1" />
    <dof index="287" value="54.031009894519883" cell_index="14" cell_dof_index="3" />
    <dof index="288" value="55.615137955387361" cell_index="14" cell_dof_index="5" />
  </function_data>
</dolfin>
